vscode_dl/__init__.py
vscode_dl/extensions.yaml
vscode_dl/get.py
vscode_dl/index.html
vscode_dl/vscode_dl.py
vscode_dl-1.0.2.dist-info/LICENSE
vscode_dl-1.0.2.dist-info/METADATA
vscode_dl-1.0.2.dist-info/WHEEL
vscode_dl-1.0.2.dist-info/entry_points.txt
vscode_dl-1.0.2.dist-info/top_level.txt
vscode_dl-1.0.2.dist-info/RECORD
