Metadata-Version: 2.1
Name: vscode-dl
Version: 1.0.2
Summary: Visual Studio Code and extensions downloader for offline installations
Home-page: https://rene-d.github.io/vscode-dl/
Author: Rene Devichi
Author-email: rene.github@gmail.com
License: Public domain
Project-URL: Source Code, https://github.com/rene-d/vscode-dl
Project-URL: Bug Reports, https://github.com/rene-d/vscode-dl/issues
Keywords: vscode,visualstudiocode
Platform: UNKNOWN
Classifier: License :: Public Domain
Classifier: Programming Language :: Python :: 3 :: Only
Classifier: Programming Language :: Python :: 3.6
Classifier: Programming Language :: Python :: 3.7
Classifier: Programming Language :: Python :: 3.8
Classifier: Topic :: System :: Archiving :: Mirroring
Classifier: Topic :: System :: Installation/Setup
Classifier: Development Status :: 5 - Production/Stable
Classifier: Operating System :: OS Independent
Requires-Python: >=3.6
Requires-Dist: requests
Requires-Dist: python-dateutil
Requires-Dist: PyYAML
Requires-Dist: requests-cache
